{
    "IcoMoonType": "selection",
    "icons": [
        {
            "icon": {
                "paths": [
                    "M86 597.999q0-98 68-167t166-69h448q70 0 120 51t50 121-50 120-120 50h-362q-44 0-76-31t-32-75 32-76 76-32h320v86h-324q-18 0-18 21t18 21h366q34 0 60-25t26-59-26-60-60-26h-448q-62 0-106 44t-44 106 44 105 106 43h406v86h-406q-98 0-166-68t-68-166z"
                ],
                "isMulticolor": false,
                "isMulticolor2": false,
                "tags": [
                    "attachment"
                ],
                "defaultCode": 58044,
                "grid": 0
            },
            "properties": {
                "id": 20,
                "order": 6,
                "ligatures": "",
                "prevSize": 32,
                "code": 58044,
                "name": "attachment"
            },
            "setIdx": 0,
            "setId": 3,
            "iconIdx": 19
        },
        {
            "icon": {
                "paths": [
                    "M316 397.999l196 196 196-196 60 60-256 256-256-256z"
                ],
                "isMulticolor": false,
                "isMulticolor2": false,
                "tags": [
                    "keyboard_arrow_down"
                ],
                "defaultCode": 58131,
                "grid": 0
            },
            "properties": {
                "id": 22,
                "order": 5,
                "ligatures": "",
                "prevSize": 32,
                "code": 58131,
                "name": "arrow_down"
            },
            "setIdx": 0,
            "setId": 3,
            "iconIdx": 21
        },
        {
            "icon": {
                "paths": [
                    "M214 831.999h596v86h-596v-86zM810 447.999l-298 298-298-298h170v-256h256v256h170z"
                ],
                "isMulticolor": false,
                "isMulticolor2": false,
                "tags": [
                    "get_app"
                ],
                "defaultCode": 59524,
                "grid": 0
            },
            "properties": {
                "id": 51,
                "order": 4,
                "ligatures": "",
                "prevSize": 32,
                "code": 59524,
                "name": "download"
            },
            "setIdx": 0,
            "setId": 3,
            "iconIdx": 50
        },
        {
            "icon": {
                "paths": [
                    "M512 405.333c70 0 128 58 128 128s-58 128-128 128-128-58-128-128 58-128 128-128zM512 747.333c118 0 214-96 214-214s-96-214-214-214-214 96-214 214 96 214 214 214zM512 213.333c214 0 396 132 470 320-74 188-256 320-470 320s-396-132-470-320c74-188 256-320 470-320z"
                ],
                "isMulticolor": false,
                "isMulticolor2": false,
                "tags": [
                    "visibility"
                ],
                "defaultCode": 59636,
                "grid": 0
            },
            "properties": {
                "id": 61,
                "order": 3,
                "ligatures": "",
                "prevSize": 32,
                "code": 59636,
                "name": "eye"
            },
            "setIdx": 0,
            "setId": 3,
            "iconIdx": 60
        },
        {
            "icon": {
                "paths": [
                    "M768 170h128v342h-342v384c0 24-18 42-42 42h-86c-24 0-42-18-42-42v-470h426v-170h-42v42c0 24-18 44-42 44h-512c-24 0-44-20-44-44v-170c0-24 20-42 44-42h512c24 0 42 18 42 42v42z"
                ],
                "attrs": [],
                "isMulticolor": false,
                "isMulticolor2": false,
                "tags": [
                    "format_paint"
                ],
                "defaultCode": 57923,
                "grid": 24
            },
            "attrs": [],
            "properties": {
                "order": 3,
                "ligatures": "format_paint",
                "id": 0,
                "prevSize": 24,
                "code": 57923,
                "name": "format_paint"
            },
            "setIdx": 1,
            "setId": 2,
            "iconIdx": 0
        },
        {
            "icon": {
                "paths": [
                    "M786 452l152-154v384h-384l156-154c-60-50-136-80-220-80-152 0-280 98-324 234l-100-32c58-178 226-308 424-308 114 0 218 42 296 110z"
                ],
                "attrs": [],
                "isMulticolor": false,
                "isMulticolor2": false,
                "tags": [
                    "redo"
                ],
                "defaultCode": 57690,
                "grid": 24
            },
            "attrs": [],
            "properties": {
                "order": 4,
                "ligatures": "redo",
                "id": 1,
                "prevSize": 24,
                "code": 57690,
                "name": "redo"
            },
            "setIdx": 1,
            "setId": 2,
            "iconIdx": 1
        },
        {
            "icon": {
                "paths": [
                    "M534 342c198 0 364 130 424 308l-100 32c-44-136-172-234-324-234-84 0-160 30-220 80l156 154h-384v-384l152 154c78-68 182-110 296-110z"
                ],
                "attrs": [],
                "isMulticolor": false,
                "isMulticolor2": false,
                "tags": [
                    "undo"
                ],
                "defaultCode": 57702,
                "grid": 24
            },
            "attrs": [],
            "properties": {
                "order": 2,
                "ligatures": "undo",
                "id": 2,
                "prevSize": 24,
                "code": 57702,
                "name": "undo"
            },
            "setIdx": 1,
            "setId": 2,
            "iconIdx": 2
        }
    ],
    "height": 1024,
    "metadata": {
        "name": "Simditor-R"
    },
    "preferences": {
        "showGlyphs": true,
        "showCodes": true,
        "showQuickUse": true,
        "showQuickUse2": true,
        "showSVGs": true,
        "fontPref": {
            "prefix": "simditor-r-icon-",
            "metadata": {
                "fontFamily": "Simditor-R",
                "majorVersion": 1,
                "minorVersion": 0
            },
            "metrics": {
                "emSize": 1024,
                "baseline": 6.25,
                "whitespace": 50
            },
            "embed": false,
            "noie8": true,
            "ie7": false,
            "showVersion": false,
            "showMetadata": false,
            "showMetrics": false,
            "cssVars": true
        },
        "imagePref": {
            "prefix": "icon-",
            "png": true,
            "useClassSelector": true,
            "color": 0,
            "bgColor": 16777215,
            "classSelector": ".icon"
        },
        "historySize": 100
    }
}